{
  "name": "Bhashkar",
  "taglines": [
    "Senior Frontend Developer",
    "UI/UX Enthusiast",
    "Open Source Contributor"
  ],
  "contact": {
    "location": "San Francisco, CA",
    "phone": "+1-555-0199",
    "email": "bhashkar@example.com"
  },
  "social": [
    {
      "platform": "GitHub",
      "url": "https://github.com/bhashkar",
      "icon": "fab fa-github"
    },
    {
      "platform": "LinkedIn",
      "url": "https://linkedin.com/in/bhashkar",
      "icon": "fab fa-linkedin-in"
    }
  ],
  "profilePic": "Bhashkar.jpg"
}